idcodes/CMakeLists.txt
idcodes/README.md
idcodes/__init__.py
idcodes/idcodes.cpython-312-x86_64-linux-gnu.so
idcodes/idcodes_encoder.cpython-312-x86_64-linux-gnu.so
idcodes/idcodes_gf.cpython-312-x86_64-linux-gnu.so
idcodes/idcodes_rmid.cpython-312-x86_64-linux-gnu.so
idcodes/idcodes_rs2id.cpython-312-x86_64-linux-gnu.so
idcodes/idcodes_rsid.cpython-312-x86_64-linux-gnu.so
idcodes/idcodes_sha1id.cpython-312-x86_64-linux-gnu.so
idcodes/idcodes_sha256id.cpython-312-x86_64-linux-gnu.so
idcodes/pybind_idcodes.cpp
idcodes/version
idcodes/encoder/encoder.cpp
idcodes/encoder/gf/gf.cpp
idcodes/encoder/rmid/rmid.cpp
idcodes/encoder/rs2id/rs2id.cpp
idcodes/encoder/rsid/rsid.cpp
idcodes/encoder/sha1id/sha1id.cpp
idcodes/encoder/sha256id/sha256id.cpp
idcodes-0.2.8.dist-info/licenses/LICENSE
idcodes-0.2.8.dist-info/METADATA
idcodes-0.2.8.dist-info/WHEEL
idcodes-0.2.8.dist-info/top_level.txt
idcodes-0.2.8.dist-info/RECORD
