Metadata-Version: 2.4
Name: idcodes
Version: 0.2.8
Summary: Python bindings for IDCODES Library
Author: EcoLogic Computing GmbH
Author-email: info@ecologic-computing.com
License: Proprietary Software License Agreement
Classifier: Programming Language :: Python :: 3
Classifier: Programming Language :: Python :: 3.12
Classifier: Operating System :: OS Independent
Requires-Python: >=3.12
License-File: LICENSE
Requires-Dist: pybind11>=2.6.0
Requires-Dist: setuptools
Requires-Dist: wheel
Requires-Dist: scikit-build-core
Dynamic: author
Dynamic: author-email
Dynamic: license
Dynamic: license-file
